{"0": ",", "1": "load", "2": "sets", "3": "with", "4": "on", "5": "get", "6": "bread", "7": "glasses", "8": "glass", "9": "cucumber", "10": "refrigerator/cabinets/drawers", "11": "towel", "12": "potato", "13": "a", "14": "mugs", "15": "stack", "16": "into", "17": "none", "18": "peel", "19": "3", "20": "items", "21": "cutting", "22": "water", "23": "pitcher", "24": "pour", "25": "almond", "26": "unload", "27": "clear", "28": "utensils", "29": "dishwasher", "30": "set", "31": "butter", "32": "large/small", "33": "open/close", "34": "slice", "35": "from", "36": "jelly", "37": "sponge", "38": "bowls", "39": "spread", "40": "jar", "41": "clean", "42": "pan", "43": "each", "44": "table", "45": "get/replace", "46": "plates", "47": "cabinets", "48": "of", "49": "board", "50": "plate"}